supersullytools/__init__.py
supersullytools/gcalendar_access.py
supersullytools/llm/__init__.py
supersullytools/llm/agent.py
supersullytools/llm/completions.py
supersullytools/llm/trackers.py
supersullytools/llm/agent_tools/__init__.py
supersullytools/llm/agent_tools/demo_tools.py
supersullytools/llm/agent_tools/duckduckgo.py
supersullytools/streamlit/__init__.py
supersullytools/streamlit/chat_agent_utils.py
supersullytools/streamlit/misc.py
supersullytools/streamlit/paginator.py
supersullytools/streamlit/sessions.py
supersullytools/utils/__init__.py
supersullytools/utils/common_init.py
supersullytools/utils/fuzzy_search.py
supersullytools/utils/media_manager.py
supersullytools/utils/misc.py
supersullytools/utils/reminder_templates.py
supersullytools-14.2.0.dist-info/LICENSE
supersullytools-14.2.0.dist-info/METADATA
supersullytools-14.2.0.dist-info/WHEEL
supersullytools-14.2.0.dist-info/top_level.txt
supersullytools-14.2.0.dist-info/RECORD
