Metadata-Version: 2.2
Name: supersullytools
Version: 14.2.0
Summary: This is a Python package that brings together a suite of utilities and helpers across several domains of software development.
Author-email: Sully <sully@sadburger.com>
License: The MIT License (MIT)
Project-URL: Homepage, https://github.com/msull/supersullytools
Keywords: streamlit,dynamodb
Classifier: License :: OSI Approved :: MIT License
Classifier: Programming Language :: Python
Classifier: Programming Language :: Python :: 3
Requires-Python: >=3.10
License-File: LICENSE
Provides-Extra: dev
Requires-Dist: boto3; extra == "dev"
Requires-Dist: black; extra == "dev"
Requires-Dist: boto3-stubs[bedrock-runtime,dynamodb]; extra == "dev"
Requires-Dist: bumpver; extra == "dev"
Requires-Dist: cryptography; extra == "dev"
Requires-Dist: diskcache; extra == "dev"
Requires-Dist: duckduckgo_search; extra == "dev"
Requires-Dist: humanize; extra == "dev"
Requires-Dist: invoke; extra == "dev"
Requires-Dist: invoke; extra == "dev"
Requires-Dist: logzero; extra == "dev"
Requires-Dist: jsonref; extra == "dev"
Requires-Dist: numpy; extra == "dev"
Requires-Dist: openai; extra == "dev"
Requires-Dist: pandas; extra == "dev"
Requires-Dist: pip-tools; extra == "dev"
Requires-Dist: pydantic>2; extra == "dev"
Requires-Dist: pydub; extra == "dev"
Requires-Dist: pypdfium2; extra == "dev"
Requires-Dist: pytest; extra == "dev"
Requires-Dist: pytest-cov; extra == "dev"
Requires-Dist: pytest-docker; extra == "dev"
Requires-Dist: pytest-mock; extra == "dev"
Requires-Dist: questionary; extra == "dev"
Requires-Dist: ruff; extra == "dev"
Requires-Dist: simplesingletable>=1.6; extra == "dev"
Requires-Dist: smart-open; extra == "dev"
Requires-Dist: streamlit; extra == "dev"
Requires-Dist: streamlit-extras; extra == "dev"
Requires-Dist: ulid-py; extra == "dev"
Requires-Dist: watchdog; extra == "dev"
Provides-Extra: build
Requires-Dist: build; extra == "build"
Requires-Dist: twine; extra == "build"
